<?xml version="1.0" encoding="UTF-8"?>
<con:soapui-project id="196406ef-c19b-43ac-a004-4bf67d86cba1" activeEnvironment="Default" name="REST Project 1" soapui-version="5.7.0" xmlns:con="http://eviware.com/soapui/config"><con:settings><con:setting id="com.eviware.soapui.impl.wsdl.actions.iface.tools.soapui.TestRunnerAction@values-local"><![CDATA[<xml-fragment xmlns:con="http://eviware.com/soapui/config">
  <con:entry key="Report Format(s)" value=""/>
  <con:entry key="Host:Port" value=""/>
  <con:entry key="Export JUnit Results" value="false"/>
  <con:entry key="Export All" value="false"/>
  <con:entry key="Save After" value="false"/>
  <con:entry key="Add Settings" value="false"/>
  <con:entry key="WSS Password Type" value=""/>
  <con:entry key="TestSuite" value="TestSuite 1"/>
  <con:entry key="Endpoint" value=""/>
  <con:entry key="Select Report Type" value=""/>
  <con:entry key="System Properties" value=""/>
  <con:entry key="Password" value=""/>
  <con:entry key="Print Report" value="false"/>
  <con:entry key="Open Report" value="false"/>
  <con:entry key="Export JUnit Results with test properties" value="false"/>
  <con:entry key="Global Properties" value=""/>
  <con:entry key="Project Properties" value=""/>
  <con:entry key="Project Password" value=""/>
  <con:entry key="TestCase" value="TestCase 1"/>
  <con:entry key="Username" value=""/>
  <con:entry key="user-settings.xml Password" value=""/>
  <con:entry key="TestRunner Path" value=""/>
  <con:entry key="Environment" value="Default"/>
  <con:entry key="Coverage Report" value="false"/>
  <con:entry key="Enable UI" value="false"/>
  <con:entry key="Root Folder" value=""/>
  <con:entry key="Ignore Errors" value="false"/>
  <con:entry key="Domain" value=""/>
  <con:entry key="Tool Args" value=""/>
  <con:entry key="Save Project" value="false"/>
</xml-fragment>]]></con:setting></con:settings><con:interface xsi:type="con:RestService" id="3ea0eb8d-0840-4673-91c4-91615c2c348a" wadlVersion="http://wadl.dev.java.net/2009/02" name="https://restcountries.com" type="rest" xmlns:xsi="http://www.w3.org/2001/XMLSchema-instance"><con:settings/><con:definitionCache type="TEXT" rootPart=""/><con:endpoints><con:endpoint>https://restcountries.com</con:endpoint></con:endpoints><con:resource name="All" path="/v3.1/all" id="c8c53f8d-4913-4d3a-a1a5-13cabc1c901d"><con:settings/><con:parameters/><con:method name="All 1" id="389ffa93-5a0c-48bc-b96f-4d130c1f70f6" method="GET"><con:settings/><con:parameters/><con:representation type="RESPONSE"><con:mediaType>application/json</con:mediaType><con:status>200</con:status><con:params/><con:element>Response</con:element></con:representation><con:request name="Request 1" id="9d0f8153-b074-45f2-833f-531d51d36485" mediaType="application/json"><con:settings><con:setting id="com.eviware.soapui.impl.wsdl.WsdlRequest@request-headers">&lt;xml-fragment/></con:setting></con:settings><con:endpoint>https://restcountries.com</con:endpoint><con:request/><con:originalUri>https://restcountries.com/v3.1/all</con:originalUri><con:credentials><con:authType>No Authorization</con:authType></con:credentials><con:jmsConfig JMSDeliveryMode="PERSISTENT"/><con:jmsPropertyConfig/><con:parameters/></con:request></con:method></con:resource></con:interface><con:interface xsi:type="con:RestService" id="9c638159-54dd-43df-8f37-908e2eb30a54" wadlVersion="http://wadl.dev.java.net/2009/02" name="https://restcountries.com" type="rest" xmlns:xsi="http://www.w3.org/2001/XMLSchema-instance"><con:settings/><con:definitionCache type="TEXT" rootPart=""/><con:endpoints><con:endpoint>https://restcountries.com</con:endpoint></con:endpoints><con:resource name="United" path="/v3.1/name/united{countryName}" id="86397873-305f-4730-9907-5f9ad27dca08"><con:settings/><con:parameters><con:parameter><con:name>countryName</con:name><con:value/><con:style>TEMPLATE</con:style><con:default/><con:description xsi:nil="true"/></con:parameter></con:parameters><con:method name="United 1" id="198e1ffb-ed6d-4eb8-860b-e44e0ff9b71a" method="GET"><con:settings/><con:parameters/><con:representation type="RESPONSE"><con:mediaType>application/json</con:mediaType><con:status>200</con:status><con:params/><con:element>Response</con:element></con:representation><con:representation type="FAULT"><con:mediaType>application/json</con:mediaType><con:status>404</con:status><con:params/><con:element xmlns:unit="https://restcountries.com/v3.1/name/united">unit:Fault</con:element></con:representation><con:request name="Request 1" id="3db7d3ea-acbc-408d-b4fd-6fb069aeb0ee" mediaType="application/json"><con:settings><con:setting id="com.eviware.soapui.impl.wsdl.WsdlRequest@request-headers">&lt;xml-fragment/></con:setting></con:settings><con:endpoint>https://restcountries.com</con:endpoint><con:request/><con:originalUri>https://restcountries.com/v3.1/name/united</con:originalUri><con:credentials><con:authType>No Authorization</con:authType></con:credentials><con:jmsConfig JMSDeliveryMode="PERSISTENT"/><con:jmsPropertyConfig/><con:parameters/><con:parameterOrder><con:entry>countryName</con:entry></con:parameterOrder></con:request></con:method></con:resource></con:interface><con:interface xsi:type="con:RestService" id="365651dd-143f-4fc4-9663-19062d8573d3" wadlVersion="http://wadl.dev.java.net/2009/02" name="https://restcountries.com" type="rest" xmlns:xsi="http://www.w3.org/2001/XMLSchema-instance"><con:settings/><con:definitionCache/><con:endpoints><con:endpoint>https://restcountries.com</con:endpoint></con:endpoints><con:resource name="Aruba" path="/v3.1/name/aruba" id="3682443e-e218-44ea-ab2d-b407d14dea93"><con:settings/><con:parameters><con:parameter><con:name>fullText</con:name><con:value>true</con:value><con:style>QUERY</con:style><con:default>true</con:default><con:path xsi:nil="true"/><con:description xsi:nil="true"/></con:parameter></con:parameters><con:method name="Aruba 1" id="4a41ee62-eed1-4f1a-89fb-b28fa1174d07" method="GET"><con:settings/><con:parameters/><con:representation type="RESPONSE"><con:mediaType>application/json</con:mediaType><con:status>200</con:status><con:params/><con:element>Response</con:element></con:representation><con:request name="Request 1" id="ba7d51e0-d679-4b8d-a38e-15d09c90e9d2" mediaType="application/json"><con:settings><con:setting id="com.eviware.soapui.impl.wsdl.WsdlRequest@request-headers">&lt;xml-fragment/></con:setting></con:settings><con:endpoint>https://restcountries.com</con:endpoint><con:request/><con:originalUri>https://restcountries.com/v3.1/name/aruba</con:originalUri><con:credentials><con:authType>No Authorization</con:authType></con:credentials><con:jmsConfig JMSDeliveryMode="PERSISTENT"/><con:jmsPropertyConfig/><con:parameters><entry key="fullText" value="false" xmlns="http://eviware.com/soapui/config"/></con:parameters><con:parameterOrder><con:entry>fullText</con:entry></con:parameterOrder></con:request></con:method></con:resource></con:interface><con:testSuite id="018f0d9a-c856-4d41-9eac-3d03b41e267b" name="TestSuite 1"><con:settings/><con:runType>SEQUENTIAL</con:runType><con:testCase id="ddf523ec-654e-4a7d-8764-e4bb8586eee2" failOnError="true" failTestCaseOnErrors="true" keepSession="false" maxResults="0" name="TestCase 1" searchProperties="true"><con:settings/><con:testStep type="restrequest" name="GetCountries" id="04405f89-9351-42e7-ad66-d4232b4a1344"><con:settings/><con:config service="https://restcountries.com" resourcePath="/v3.1/all" methodName="All 1" xsi:type="con:RestRequestStep" xmlns:xsi="http://www.w3.org/2001/XMLSchema-instance"><con:restRequest name="GetCountries" id="9d0f8153-b074-45f2-833f-531d51d36485" mediaType="application/json"><con:settings><con:setting id="com.eviware.soapui.impl.wsdl.WsdlRequest@request-headers">&lt;xml-fragment/></con:setting></con:settings><con:endpoint>https://restcountries.com</con:endpoint><con:request/><con:originalUri>https://restcountries.com/v3.1/all</con:originalUri><con:assertion type="Simple Contains" id="f3e20e5e-f03a-41c3-b1f9-ffcb4172442d" name="Contains"><con:configuration><token>Europe</token><ignoreCase>false</ignoreCase><useRegEx>false</useRegEx></con:configuration></con:assertion><con:credentials><con:authType>No Authorization</con:authType></con:credentials><con:jmsConfig JMSDeliveryMode="PERSISTENT"/><con:jmsPropertyConfig/><con:parameters/></con:restRequest></con:config></con:testStep><con:testStep type="restrequest" name="GetCountriesByName" id="b60a7d21-555f-46c1-9631-214ee1566369"><con:settings/><con:config service="https://restcountries.com" resourcePath="/v3.1/name/united{countryName}" methodName="United 1" xsi:type="con:RestRequestStep" xmlns:xsi="http://www.w3.org/2001/XMLSchema-instance"><con:restRequest name="GetCountriesByName" id="3db7d3ea-acbc-408d-b4fd-6fb069aeb0ee" mediaType="application/json"><con:settings><con:setting id="com.eviware.soapui.impl.wsdl.WsdlRequest@request-headers">&lt;xml-fragment/></con:setting></con:settings><con:endpoint>https://restcountries.com</con:endpoint><con:request/><con:originalUri>https://restcountries.com/v3.1/name/united</con:originalUri><con:assertion type="Simple Contains" id="7754f647-c09e-4b31-bc93-e20b97c0969a" name="Contains"><con:configuration><token>United Arab Emirates</token><ignoreCase>false</ignoreCase><useRegEx>false</useRegEx></con:configuration></con:assertion><con:credentials><con:authType>No Authorization</con:authType></con:credentials><con:jmsConfig JMSDeliveryMode="PERSISTENT"/><con:jmsPropertyConfig/><con:parameters/><con:parameterOrder><con:entry>countryName</con:entry></con:parameterOrder></con:restRequest></con:config></con:testStep><con:properties/></con:testCase><con:properties/><con:setupScript>log.info ("This is will before TestSuite1")</con:setupScript><con:tearDownScript>log.info ("This is will after TestSuite1")</con:tearDownScript></con:testSuite><con:properties/><con:wssContainer/><con:oAuth2ProfileContainer/><con:oAuth1ProfileContainer/></con:soapui-project>